fut_card_creator/__init__.py
fut_card_creator/fut_card_creator.py
fut_card_creator/utils.py
fut_card_creator/fonts/DINPro CondBold.otf
fut_card_creator/fonts/DINPro Condensed.otf
fut_card_creator/images/card_templates/bronze_rare.png
fut_card_creator/images/card_templates/future_star.png
fut_card_creator/images/card_templates/gold.png
fut_card_creator/images/card_templates/icon.png
fut_card_creator/images/card_templates/rare_gold.png
fut_card_creator/images/card_templates/silver_rare.png
fut_card_creator/images/card_templates/tots.png
fut_card_creator/images/card_templates/totw.png
fut_card_creator/images/card_templates/toty.png
fut_card_creator/images/club_logo_cache/al_hilal.png
fut_card_creator/images/club_logo_cache/arsenal.png
fut_card_creator/images/club_logo_cache/atlético_de_madrid.png
fut_card_creator/images/club_logo_cache/bergamo_calcio.png
fut_card_creator/images/club_logo_cache/fc_barcelona.png
fut_card_creator/images/club_logo_cache/fc_bayern_münchen.png
fut_card_creator/images/club_logo_cache/leverkusen.png
fut_card_creator/images/club_logo_cache/manchester_city.png
fut_card_creator/images/club_logo_cache/manchester_utd.png
fut_card_creator/images/club_logo_cache/ol.png
fut_card_creator/images/club_logo_cache/paris_saint-germain.png
fut_card_creator/images/club_logo_cache/real_madrid.png
fut_card_creator/images/nation_cache/Argentina.png
fut_card_creator/images/nation_cache/Belgium.png
fut_card_creator/images/nation_cache/Brazil.png
fut_card_creator/images/nation_cache/Canada.png
fut_card_creator/images/nation_cache/Croatia.png
fut_card_creator/images/nation_cache/France.png
fut_card_creator/images/nation_cache/Germany.png
fut_card_creator/images/nation_cache/Norway.png
fut_card_creator/images/nation_cache/Portugal.png
fut_card_creator/images/nation_cache/Spain.png
fut_card_creator/images/nation_cache/england.png
fut_card_creator-1.3.3.dist-info/METADATA
fut_card_creator-1.3.3.dist-info/WHEEL
fut_card_creator-1.3.3.dist-info/top_level.txt
fut_card_creator-1.3.3.dist-info/RECORD
