Metadata-Version: 2.1
Name: fut-card-creator
Version: 1.3.3
Summary: A package that allows you to create custom FUT cards
Home-page: https://github.com/AngelFireLA/FutCardCreator
Author: AngelFire
Requires-Python: >=3.6
Requires-Dist: Pillow >=8.0.0
Requires-Dist: requests >=2.0.0
Requires-Dist: fuzzywuzzy[speedup] >=0.18.0
Requires-Dist: python-Levenshtein >=0.12.0
